{
  "sources": [
    {
      "title": "Twitter @吴说区块链",
      "feedUrl": "https://rsshub.app/twitter/user/wublockchain12",
      "siteUrl": "https://x.com/wublockchain12",
      "articles": [
        {
          "id": "https://twitter.com/wublockchain12/status/1826191941614162356",
          "author": "吴说区块链",
          "description": "Re 相关记录必须保持连贯，资金链路需完整，不要出现大额资金来源不明，远超炒币收益且解释不清的情况。如无必要，可降低OTC频率，仅在必要时候选择靠谱的渠道出币。",
          "link": "https://x.com/wublockchain12/status/1826191941614162356",
          "publishedOn": "2024-08-21T09:37:42.000Z",
          "wordCount": 6,
          "title": "Re 相关记录必须保持连贯，资金链路需完整，不要出现大额资金来源不明，远超炒币收益且解释不清的情况。如无必要，可降低OTC频率，仅在必要时候选择靠谱的渠道出...",
          "imageUrl": null
        },
        {
          "id": "https://twitter.com/wublockchain12/status/1826191939441426444",
          "author": "吴说区块链",
          "description": "《肖飒：“虚拟资产交易”进入洗钱罪司法解释 如何保护自己》对炒币资金来源进行留痕留底。要对自己用于炒币的资金来源进行存证，做到一但被询问，能够一五一十说清楚。对自己在平台上购买、出售加密资产的记录进行留痕留底。这部分证据非常重要。阅读全文： http://wublock123.com/index.php?m=content&c=index&a=show&catid=47&id=30547",
          "link": "https://x.com/wublockchain12/status/1826191939441426444",
          "publishedOn": "2024-08-21T09:37:42.000Z",
          "wordCount": 6,
          "title": "《肖飒：“虚拟资产交易”进入洗钱罪司法解释 如何保护自己》对炒币资金来源进行留痕留底。要对自己用于炒币的资金来源进行存证，做到一但被询问，能够一五一十...",
          "imageUrl": null
        },
        {
          "id": "https://twitter.com/wublockchain12/status/1826185439365234836",
          "author": "吴说区块链",
          "description": "吴说获悉，据 Arkham 监测，Mt Gox 于本日 16:49 UTC+8 向 Bitstamp 转移了 1,264.7 BTC，价值约 7,536 万美元。转移之后，Mt.Gox 现在持有 34,164 BTC（价值 20.3 亿美元）。\nhttp://wublock123.com/index.php?m=content&c=index&a=show&catid=6&id=30545",
          "link": "https://x.com/wublockchain12/status/1826185439365234836",
          "publishedOn": "2024-08-21T09:11:52.000Z",
          "wordCount": 6,
          "title": "吴说获悉，据 Arkham 监测，Mt Gox 于本日 16:49 UTC+8 向 Bitstamp 转移了 1,264.7 BTC，价值约 7,536 万美元。转移之后，Mt.Gox 现在持有 34,164 BTC（价值 20...",
          "imageUrl": null
        },
        {
          "id": "https://twitter.com/wublockchain12/status/1826181760239214679",
          "author": "吴说区块链",
          "description": "Bitwise 报告指出，尽管第二季度比特币价格下跌了 12% ，但机构投资者持有的比特币 ETF 数量却显著增加，同比增长 14% 至 1100 家。机构投资者的持仓占比也从 18.74% 增至 21.15% ，持有的比特币 ETF 总资产管理规模达到 110 亿美元。 Bitwise 首席投资官 Matt Hougan…",
          "link": "https://x.com/wublockchain12/status/1826181760239214679",
          "publishedOn": "2024-08-21T08:57:15.000Z",
          "wordCount": 6,
          "title": "Bitwise 报告指出，尽管第二季度比特币价格下跌了 12% ，但机构投资者持有的比特币 ETF 数量却显著增加，同比增长 14% 至 1100 家。机构投资者的持仓占比也从 18...",
          "imageUrl": null
        },
        {
          "id": "https://twitter.com/wublockchain12/status/1826181599609975135",
          "author": "吴说区块链",
          "description": "吴说获悉，OKX 宣布将于北京时间 8 月 29 日 16:00 下架 DMAILUSDT、VNEOMUSDT、RENUSDT 等永续合约交易，并将于 8 月 21 日 14:00 下架 DMAILUSDT、VNEOMUSDT、RENUSDT 币对杠杆交易。 http://wublock123.com/index.php?m=content&c=index&a=show&catid=7&id=30543",
          "link": "https://x.com/wublockchain12/status/1826181599609975135",
          "publishedOn": "2024-08-21T08:56:36.000Z",
          "wordCount": 6,
          "title": "吴说获悉，OKX 宣布将于北京时间 8 月 29 日 16:00 下架 DMAILUSDT、VNEOMUSDT、RENUSDT 等永续合约交易，并将于 8 月 21 日 14:00 下架 DMAILUSDT、VNEOMUSDT、...",
          "imageUrl": null
        },
        {
          "id": "https://twitter.com/wublockchain12/status/1826170362784309740",
          "author": "吴说区块链",
          "description": "吴说获悉，TON 基金会最近举办了 Open League 黑客松，GameFi & Onboarding  获奖者包括 Cat Gold Miner、Chick Coop 和 Hamsterdam；Socai Web3 获奖者包括 Boosteam、Overleap 和 Tontch；DeFi 获奖者包括 SettleTON、TON Hedge 和 Curdle Protocol；eCommerce 获奖者包括 InOne、Unpacks 和…",
          "link": "https://x.com/wublockchain12/status/1826170362784309740",
          "publishedOn": "2024-08-21T08:11:57.000Z",
          "wordCount": 6,
          "title": "吴说获悉，TON 基金会最近举办了 Open League 黑客松，GameFi & Onboarding 获奖者包括 Cat Gold Miner、Chick Coop 和 Hamsterdam；Socai Web3 获奖者包括 Boos...",
          "imageUrl": null
        },
        {
          "id": "https://twitter.com/wublockchain12/status/1826167851704791061",
          "author": "吴说区块链",
          "description": "吴说获悉，萨尔瓦多总统办公室国家比特币办公室（ONBTC）发推表示，很快将开始为 8 万名萨尔瓦多公务员提供 Bitcoin 指导和认证。该办公室负责人 Stacy Herbert 表示，除了创建 CUBO，编写新的 K-8 比特币工作手册并将比特币开源课程 Mi Primer Bitcoin 和 Node Nation引入公立学校外，还在帮助 ESIAP…",
          "link": "https://x.com/wublockchain12/status/1826167851704791061",
          "publishedOn": "2024-08-21T08:01:59.000Z",
          "wordCount": 6,
          "title": "吴说获悉，萨尔瓦多总统办公室国家比特币办公室（ONBTC）发推表示，很快将开始为 8 万名萨尔瓦多公务员提供 Bitcoin 指导和认证。该办公室负责人 Stacy Herbert ...",
          "imageUrl": null
        },
        {
          "id": "https://twitter.com/wublockchain12/status/1826152807763948036",
          "author": "吴说区块链",
          "description": "吴说获悉，Binance 宣布将于 8 月 23 日 11:00 UTC+8 移除并停止以下现货交易对的交易：ARKM/TUSD、CHZ/EUR、ENA/EUR、FIRO/BTC、IOTA/FDUSD、JOE/TRY、OMNI/BNB、REZ/BNB 和 SUPER/FDUSD。Binance…",
          "link": "https://x.com/wublockchain12/status/1826152807763948036",
          "publishedOn": "2024-08-21T07:02:12.000Z",
          "wordCount": 6,
          "title": "吴说获悉，Binance 宣布将于 8 月 23 日 11:00 UTC+8 移除并停止以下现货交易对的交易：ARKM/TUSD、CHZ/EUR、ENA/EUR、FIRO/BTC、IOTA/FDUSD、JOE/TRY、OMNI/BNB...",
          "imageUrl": null
        },
        {
          "id": "https://twitter.com/wublockchain12/status/1826149735427940580",
          "author": "吴说区块链",
          "description": "吴说获悉，据 Tronscan 区块浏览器，8 月 20 日，Tron 网络协议收入达 2,400 万 TRX（约 388 万美元），创下历史新高，这应与近期 SunPump 推出和带动的 Tron 网络上 Meme 行情活跃有关。Tron 协议收入包括用户为获取能量资源和支付交易而销毁的 TRX。https://www.wublock123.com/index.php?m=content&c=index&a=show&catid=48&id=30539",
          "link": "https://x.com/wublockchain12/status/1826149735427940580",
          "publishedOn": "2024-08-21T06:49:59.000Z",
          "wordCount": 6,
          "title": "吴说获悉，据 Tronscan 区块浏览器，8 月 20 日，Tron 网络协议收入达 2,400 万 TRX（约 388 万美元），创下历史新高，这应与近期 SunPump 推出和带动的 Tron 网...",
          "imageUrl": null
        },
        {
          "id": "https://twitter.com/wublockchain12/status/1826140851459993702",
          "author": "吴说区块链",
          "description": "吴说获悉，Aptos 区块浏览器 Topaz 宣布将于 8 月 21 日起停止运营。值得注意的是，Topza 主要是 Aptos 上的一个 NFT 交易市场，还曾推出积分系统，但已几乎没有任何 NFT 交易量。https://www.wublock123.com/index.php?m=content&c=index&a=show&catid=40&id=30538",
          "link": "https://x.com/wublockchain12/status/1826140851459993702",
          "publishedOn": "2024-08-21T06:14:41.000Z",
          "wordCount": 6,
          "title": "吴说获悉，Aptos 区块浏览器 Topaz 宣布将于 8 月 21 日起停止运营。值得注意的是，Topza 主要是 Aptos 上的一个 NFT 交易市场，还曾推出积分系统，但已几乎没有...",
          "imageUrl": null
        },
        {
          "id": "https://twitter.com/wublockchain12/status/1826131255584252007",
          "author": "吴说区块链",
          "description": "Re 慢雾余弦表示，受害者的 5,547 万枚 DAI 被 Inferno Drainer 一笔钓走；经和 Scam Sniffer 分析，是其 DSProxy 合约的 owner 被钓鱼设置（SetOwner）成了钓鱼有关钱包地址，然后实施之后的盗币操作。该手法和当年对 OpenSea Wyvern Protocol 钓鱼案例类似。",
          "link": "https://x.com/wublockchain12/status/1826131255584252007",
          "publishedOn": "2024-08-21T05:36:33.000Z",
          "wordCount": 6,
          "title": "Re 慢雾余弦表示，受害者的 5,547 万枚 DAI 被 Inferno Drainer 一笔钓走；经和 Scam Sniffer 分析，是其 DSProxy 合约的 owner 被钓鱼设置（SetOwner）成了钓鱼...",
          "imageUrl": null
        },
        {
          "id": "https://twitter.com/wublockchain12/status/1826106204726374888",
          "author": "吴说区块链",
          "description": "吴说获悉，根据 SoSoValue 数据，昨日（美东时间 8 月 20 日）比特币现货 ETF 总净流入 8806.06 万美元，持续 4 日净流入。昨日灰度（Grayscale）ETF GBTC 单日净流出 1281.24 万美元。灰度（Grayscale）比特币迷你信托 ETF BTC 单日净流出 0.00 美元。昨日单日净流入最多的比特币现货 ETF…",
          "link": "https://x.com/wublockchain12/status/1826106204726374888",
          "publishedOn": "2024-08-21T03:57:01.000Z",
          "wordCount": 6,
          "title": "吴说获悉，根据 SoSoValue 数据，昨日（美东时间 8 月 20 日）比特币现货 ETF 总净流入 8806.06 万美元，持续 4 日净流入。昨日灰度（Grayscale）ETF GBTC 单日...",
          "imageUrl": null
        },
        {
          "id": "https://twitter.com/wublockchain12/status/1826105358491988130",
          "author": "吴说区块链",
          "description": "吴说获悉，根据 SoSoValue 数据，昨日（美东时间 8 月 20 日）美国以太坊现货 ETF 总净流出 648.67 万美元，持续 4 日净流出。昨日灰度（Grayscale）以太坊信托 ETF ETHE 单日净流出 3699.06 万美元。灰度（Grayscale）以太坊迷你信托 ETF ETH 单日净流出 0.00 美元。昨日单日净流入最多的以太坊现货…",
          "link": "https://x.com/wublockchain12/status/1826105358491988130",
          "publishedOn": "2024-08-21T03:53:39.000Z",
          "wordCount": 6,
          "title": "吴说获悉，根据 SoSoValue 数据，昨日（美东时间 8 月 20 日）美国以太坊现货 ETF 总净流出 648.67 万美元，持续 4 日净流出。昨日灰度（Grayscale）以太坊信托 ...",
          "imageUrl": null
        },
        {
          "id": "https://twitter.com/wublockchain12/status/1826100507490005174",
          "author": "吴说区块链",
          "description": "吴说获悉，据 Arkham 监测，Open Campus 多签合约: 0xb1…D198 于本日 11:20 UTC+8 向疑似 GSR Market: 0x56…4Fd3 转移了 1 千万枚 EDU，价值约 634 万美元。按照历史操作，该疑似 GSR Market: 0x56…4Fd3 将会把这些 EDU 转移至 Binance 或 KuCoin Deposit。该多签合约: 0xb1…D198 为 2/3…",
          "link": "https://x.com/wublockchain12/status/1826100507490005174",
          "publishedOn": "2024-08-21T03:34:22.000Z",
          "wordCount": 6,
          "title": "吴说获悉，据 Arkham 监测，Open Campus 多签合约: 0xb1…D198 于本日 11:20 UTC+8 向疑似 GSR Market: 0x56…4Fd3 转移了 1 千万枚 EDU，价值约 634 万美元。按...",
          "imageUrl": null
        },
        {
          "id": "https://twitter.com/wublockchain12/status/1826097057884680300",
          "author": "吴说区块链",
          "description": "黑山当局表示，他们逮捕了涉嫌加密诈骗计划 FutureNet 的联合创始人 Roman Ziemian。据称，该计划通过复杂的加密诈骗手段窃取了约 2,100 万美元。韩国和 Ziemian 的祖国波兰对其发布了逮捕令，指控他犯有欺诈、洗钱和盗窃罪。警方表示，他在韩国可能面临终身监禁。2020 年中期，韩国当局开始调查…",
          "link": "https://x.com/wublockchain12/status/1826097057884680300",
          "publishedOn": "2024-08-21T03:20:40.000Z",
          "wordCount": 6,
          "title": "黑山当局表示，他们逮捕了涉嫌加密诈骗计划 FutureNet 的联合创始人 Roman Ziemian。据称，该计划通过复杂的加密诈骗手段窃取了约 2,100 万美元。韩国和 Ziemian...",
          "imageUrl": null
        },
        {
          "id": "https://twitter.com/wublockchain12/status/1826092362579542494",
          "author": "吴说区块链",
          "description": "吴说获悉，据 ZachXBT 监测，某用户本日被盗取 5,540 万美元 DAI。链上数据显示，黑客: 0x5D…59d4 已将其中的 1 千万 DAI 兑换成 3,880 ETH，并转移至新地址: 0x8c…c2Dc 中；其余 DAI 也被分发至多个地址中。https://www.wublock123.com/index.php?m=content&c=index&a=show&catid=46&id=30532",
          "link": "https://x.com/wublockchain12/status/1826092362579542494",
          "publishedOn": "2024-08-21T03:02:01.000Z",
          "wordCount": 6,
          "title": "吴说获悉，据 ZachXBT 监测，某用户本日被盗取 5,540 万美元 DAI。链上数据显示，黑客: 0x5D…59d4 已将其中的 1 千万 DAI 兑换成 3,880 ETH，并转移至新地址: 0...",
          "imageUrl": null
        },
        {
          "id": "https://twitter.com/wublockchain12/status/1826086244096618753",
          "author": "吴说区块链",
          "description": "吴说获悉，glassnode 指出，自 2022 年 11 月创下周期低点以来，比特币市占率由 38.7% 增长到目前的 56.2%，以太坊市占率由 16.8% 降低到 15.2%，稳定币由 17.3% 降低到 7.4%，山寨币由 27.2% 降低到 21.3%。https://www.wublock123.com/index.php?m=content&c=index&a=show&catid=6&id=30531",
          "link": "https://x.com/wublockchain12/status/1826086244096618753",
          "publishedOn": "2024-08-21T02:37:42.000Z",
          "wordCount": 6,
          "title": "吴说获悉，glassnode 指出，自 2022 年 11 月创下周期低点以来，比特币市占率由 38.7% 增长到目前的 56.2%，以太坊市占率由 16.8% 降低到 15.2%，稳定币由 17.3%...",
          "imageUrl": null
        },
        {
          "id": "https://twitter.com/wublockchain12/status/1826082757669446070",
          "author": "吴说区块链",
          "description": "《中国洗钱刑事案件司法解释纳入“虚拟资产”有何影响？》律师指出，虚拟货币交易并不等于洗钱，更谈不上是刑事犯罪。本次两高司法解释的出台，是考虑到虚拟货币被高频的被用于洗钱的犯罪行为，为方便个案中司法审判工作的开展，进行了明确的列举，但这并不意味着在中国内地的所有虚拟货币交易行为都是洗…",
          "link": "https://x.com/wublockchain12/status/1826082757669446070",
          "publishedOn": "2024-08-21T02:23:51.000Z",
          "wordCount": 6,
          "title": "《中国洗钱刑事案件司法解释纳入“虚拟资产”有何影响？》律师指出，虚拟货币交易并不等于洗钱，更谈不上是刑事犯罪。本次两高司法解释的出台，是考虑到虚拟货币...",
          "imageUrl": null
        }
      ]
    },
    {
      "title": "Twitter @Deleted Account",
      "feedUrl": "https://rsshub.app/twitter/user/8848Community",
      "siteUrl": "https://x.com/8848Community",
      "articles": []
    }
  ],
  "cliVersion": "1.15.1"
}