{
  "sources": [
    {
      "title": "Twitter @吴说区块链",
      "feedUrl": "https://rsshub.app/twitter/user/wublockchain12",
      "siteUrl": "https://twitter.com/wublockchain12",
      "articles": [
        {
          "id": "https://twitter.com/wublockchain12/status/1751975618026279104",
          "author": "吴说区块链",
          "description": "吴说获悉，API3 宣布推出由 Polygon CDK 提供支持、基于 ZK-rollup 的订单流拍卖平台 OEV Network，自称可从所有链中使用 API3 数据源的 dApp 中捕获 OEV（Oracle 可提取价值）。OEV Network 的首个版本将是在 Ethereum 上的单一 Validium，使用 ETH 作为 Gas 代币，目前已启动 Sepolia…",
          "link": "https://twitter.com/wublockchain12/status/1751975618026279104",
          "publishedOn": "2024-01-29T14:28:32.000Z",
          "wordCount": null,
          "title": "吴说获悉，API3 宣布推出由 Polygon CDK 提供支持、基于 ZK-rollup 的订单流拍卖平台 OEV Network，自称可从所有链中使用 API3 数据源的 dApp 中捕获 OEV（Oracl...",
          "imageUrl": null
        },
        {
          "id": "https://twitter.com/wublockchain12/status/1751973376355377640",
          "author": "吴说区块链",
          "description": "吴说获悉，据 Arkham 数据，在 1 月 29 日 22:11 UTC+8，Grayscale GBTC 再次将 8668 枚 BTC 转移至 Coinbase Prime Deposit，价值约 3.64 亿美元。\nhttps://www.wublock123.com/index.php?m=content&c=index&a=show&catid=6&id=23223",
          "link": "https://twitter.com/wublockchain12/status/1751973376355377640",
          "publishedOn": "2024-01-29T14:19:37.000Z",
          "wordCount": null,
          "title": "吴说获悉，据 Arkham 数据，在 1 月 29 日 22:11 UTC+8，Grayscale GBTC 再次将 8668 枚 BTC 转移至 Coinbase Prime Deposit，价值约 3.64 亿美元。 https://www...",
          "imageUrl": null
        },
        {
          "id": "https://twitter.com/wublockchain12/status/1751972174209159224",
          "author": "吴说区块链",
          "description": "Web3 分布式 AI 培训网络 PublicAI 已完成了 200 万美元种子轮融资，参投方包括 IOBC Capital 和 Solana Foundation 等，融资将主要用于加速网络的上线和向市场推出。PublicAI 利用 Web3 构建分布式 AI 训练网络，允许任何人通过提供数据作品获得奖励，Train-To-Earn 代币经济学和 Slash/Reward…",
          "link": "https://twitter.com/wublockchain12/status/1751972174209159224",
          "publishedOn": "2024-01-29T14:14:51.000Z",
          "wordCount": null,
          "title": "Web3 分布式 AI 培训网络 PublicAI 已完成了 200 万美元种子轮融资，参投方包括 IOBC Capital 和 Solana Foundation 等，融资将主要用于加速网络的上线和向市场...",
          "imageUrl": null
        },
        {
          "id": "https://twitter.com/wublockchain12/status/1751970760833503731",
          "author": "吴说区块链",
          "description": "吴说获悉，据 Fortune 报道，PayPal 风险投资部门向数字资产初创公司 Mesh 投资了 500 万美元 PYUSD 和 150 万美元现金。Mesh 被视为 Plaid 的加密版本，可以作为一种在从加密货币交易所到钱包再到支持加密货币的金融应用程序之间转移资金的方式。Mesh 曾在去年完成了 2,200 万美元 A…",
          "link": "https://twitter.com/wublockchain12/status/1751970760833503731",
          "publishedOn": "2024-01-29T14:09:14.000Z",
          "wordCount": null,
          "title": "吴说获悉，据 Fortune 报道，PayPal 风险投资部门向数字资产初创公司 Mesh 投资了 500 万美元 PYUSD 和 150 万美元现金。Mesh 被视为 Plaid 的加密版本，可以作...",
          "imageUrl": null
        },
        {
          "id": "https://twitter.com/wublockchain12/status/1751969714740646296",
          "author": "吴说区块链",
          "description": "吴说获悉，比特小鹿宣布公司创始人兼董事会主席吴忌寒将担任首席执行官，原首席执行官孔令挥担任首席业务官，该决定将于 2024 年 3 月 1 日生效。吴忌寒表示，未来将投入资源开发前沿技术，培养强大的领导团队。https://www.wublock123.com/index.php?m=content&c=index&a=show&catid=9&id=23218",
          "link": "https://twitter.com/wublockchain12/status/1751969714740646296",
          "publishedOn": "2024-01-29T14:05:04.000Z",
          "wordCount": null,
          "title": "吴说获悉，比特小鹿宣布公司创始人兼董事会主席吴忌寒将担任首席执行官，原首席执行官孔令挥担任首席业务官，该决定将于 2024 年 3 月 1 日生效。吴忌寒表示，未...",
          "imageUrl": null
        },
        {
          "id": "https://twitter.com/wublockchain12/status/1751966987046273110",
          "author": "吴说区块链",
          "description": "吴说每日晚报",
          "link": "https://twitter.com/wublockchain12/status/1751966987046273110",
          "publishedOn": "2024-01-29T13:54:14.000Z",
          "wordCount": null,
          "title": "吴说每日晚报",
          "imageUrl": null
        },
        {
          "id": "https://twitter.com/wublockchain12/status/1751963018525831565",
          "author": "吴说区块链",
          "description": "加密衍生品交易员 Gordon Grant 表示，比特币最近的上涨得到了比特币期权未平仓合约在特定行权价的减少的鼓舞，因为对冲基金 delta 供应有限。随着 1 月 26 日星期五的月末期权到期后，短期比特币衍生品，特别是期权的未平仓合约出现了显著减少。The Block…",
          "link": "https://twitter.com/wublockchain12/status/1751963018525831565",
          "publishedOn": "2024-01-29T13:38:28.000Z",
          "wordCount": null,
          "title": "加密衍生品交易员 Gordon Grant 表示，比特币最近的上涨得到了比特币期权未平仓合约在特定行权价的减少的鼓舞，因为对冲基金 delta 供应有限。随着 1 月 26 日星...",
          "imageUrl": null
        },
        {
          "id": "https://twitter.com/wublockchain12/status/1751951249791234508",
          "author": "吴说区块链",
          "description": "财富管理公司 Creative Planning 首席市场策略师 Charlie Bilello 表示，比特币的 12 个月年化波动率已经达到了 12 年来的最低水平。根据 Bilello 的数据，该波动率水平已从 2012 年 1 月的高点 179% 下降至 2024 年 1 月的 45%。CryptoQuant 分析师 Bradley Park…",
          "link": "https://twitter.com/wublockchain12/status/1751951249791234508",
          "publishedOn": "2024-01-29T12:51:42.000Z",
          "wordCount": null,
          "title": "财富管理公司 Creative Planning 首席市场策略师 Charlie Bilello 表示，比特币的 12 个月年化波动率已经达到了 12 年来的最低水平。根据 Bilello 的数据，该波...",
          "imageUrl": null
        },
        {
          "id": "https://twitter.com/wublockchain12/status/1751949503211737514",
          "author": "吴说区块链",
          "description": "吴说获悉，OKX Jumpstart 挖矿项目 Dmail 宣布第一季早期开发者和生态系统贡献者将空投 750 万 DMAIL 代币奖励，占总量的 3.75%，涵盖付费 NFT 域名持有者、在 6 个不同月份使用过 Dmail DApp 的用户、社区贡献者、3D Crystal NFT 持有者、Dmail DApp 活跃用户和 Gitcoin 捐赠者。DMAIL 将于 1 月 30…\n\n吴说区块链: 吴说获悉，OKX 新一轮 Jumpstart 挖矿推出，用户可以质押 BTC 和 OKB 来开采 DMAIL 代币作为回报，完成 KYC 验证的韩国、俄罗斯、乌克兰、白俄罗斯等地用户可以参与；Dmail Network 是一个 AI 驱动的去中心化通信基础设施，旨在为用户提供加密电邮、统一通知以及跨多个链和 dApp 的营销。DMAIL…",
          "link": "https://twitter.com/wublockchain12/status/1751949503211737514",
          "publishedOn": "2024-01-29T12:44:45.000Z",
          "wordCount": null,
          "title": "吴说获悉，OKX Jumpstart 挖矿项目 Dmail 宣布第一季早期开发者和生态系统贡献者将空投 750 万 DMAIL 代币奖励，占总量的 3.75%，涵盖付费 NFT 域名持有者、在 6...",
          "imageUrl": null
        },
        {
          "id": "https://twitter.com/wublockchain12/status/1751945173645611236",
          "author": "吴说区块链",
          "description": "吴说获悉，据 Whale Alert，Tether 在波场网络上增发 10 亿枚 USDT。Tether 首席技术官 Paolo Ardoino 补充表示，这是一笔在波场网络已授权但未发行的交易，意味着本次增发将用于下一期发行请求和跨链交换的库存。https://www.wublock123.com/index.php?m=content&c=index&a=show&catid=43&id=23215",
          "link": "https://twitter.com/wublockchain12/status/1751945173645611236",
          "publishedOn": "2024-01-29T12:27:33.000Z",
          "wordCount": null,
          "title": "吴说获悉，据 Whale Alert，Tether 在波场网络上增发 10 亿枚 USDT。Tether 首席技术官 Paolo Ardoino 补充表示，这是一笔在波场网络已授权但未发行的交易，意味...",
          "imageUrl": null
        },
        {
          "id": "https://twitter.com/wublockchain12/status/1751943893703381041",
          "author": "吴说区块链",
          "description": "Sei Labs 计划于 2024 年上半年上线 Sei V2 升级，实施 EVM 并行化，将允许开发者在 Sei 上部署来自 Ethereum 的协议，并为部署 DeFi 协议规避智能合约风险。（DL News）https://www.wublock123.com/index.php?m=content&c=index&a=show&catid=48&id=23214",
          "link": "https://twitter.com/wublockchain12/status/1751943893703381041",
          "publishedOn": "2024-01-29T12:22:28.000Z",
          "wordCount": null,
          "title": "Sei Labs 计划于 2024 年上半年上线 Sei V2 升级，实施 EVM 并行化，将允许开发者在 Sei 上部署来自 Ethereum 的协议，并为部署 DeFi 协议规避智能合约风险。（D...",
          "imageUrl": null
        },
        {
          "id": "https://twitter.com/wublockchain12/status/1751934610156720323",
          "author": "吴说区块链",
          "description": "吴说获悉，据路透社，欧洲证券和市场管理局（ESMA）在周一提议，总部位于欧盟以外的加密公司只能在非常有限的条件下直接为欧盟内部的客户提供服务，以避免不公平竞争。ESMA 表示，采取一切必要措施，积极保护欧盟投资者和符合 MiCA 的加密资产服务提供商免受非欧盟和非 MiCA…",
          "link": "https://twitter.com/wublockchain12/status/1751934610156720323",
          "publishedOn": "2024-01-29T11:45:35.000Z",
          "wordCount": null,
          "title": "吴说获悉，据路透社，欧洲证券和市场管理局（ESMA）在周一提议，总部位于欧盟以外的加密公司只能在非常有限的条件下直接为欧盟内部的客户提供服务，以避免不公平...",
          "imageUrl": null
        },
        {
          "id": "https://twitter.com/wublockchain12/status/1751929953166426112",
          "author": "吴说区块链",
          "description": "作为首位接受比特币作为竞选捐款的美国总统候选人，罗伯特·F·肯尼迪承诺，若当选总统，将终止美国推进且永远不允许建立 CBDC，尽一切努力维持纸币。该名总统候选人认为 CBDC…",
          "link": "https://twitter.com/wublockchain12/status/1751929953166426112",
          "publishedOn": "2024-01-29T11:27:04.000Z",
          "wordCount": null,
          "title": "作为首位接受比特币作为竞选捐款的美国总统候选人，罗伯特·F·肯尼迪承诺，若当选总统，将终止美国推进且永远不允许建立 CBDC，尽一切努力维持纸币。该名总统候...",
          "imageUrl": null
        },
        {
          "id": "https://twitter.com/wublockchain12/status/1751926908005306500",
          "author": "吴说区块链",
          "description": "吴说获悉，Binance Labs Fund 表示，正常情况下，（投资的）项目方会在任何公告前通知我们，以确认提及 Binance Labs，这包含在投资合同的条款中；在 SkyArk Chronicles 团队发布公告前，我们并不知道这笔 1,500 万美元的投资和提及 Binance Labs…\n\n吴说区块链: 吴说获悉，Binance Labs Fund 表示，Binance Labs 并未参与 SkyArk Chronicles 今年的最新一轮融资，该项目仅在 2021 年通过第三季度孵化器被 Binance Labs 孵化和投资。此前，SkyArk Chronicles 官推在 1 月 12 日自宣完成由 Binance Labs 领投的 1,500…",
          "link": "https://twitter.com/wublockchain12/status/1751926908005306500",
          "publishedOn": "2024-01-29T11:14:58.000Z",
          "wordCount": null,
          "title": "吴说获悉，Binance Labs Fund 表示，正常情况下，（投资的）项目方会在任何公告前通知我们，以确认提及 Binance Labs，这包含在投资合同的条款中；在 SkyArk Chr...",
          "imageUrl": null
        },
        {
          "id": "https://twitter.com/wublockchain12/status/1751915792650875291",
          "author": "吴说区块链",
          "description": "吴说获悉，据 CoinShares，上周数字资产投资产品流出总额为 5 亿美元，其中比特币投资产品流出了 4.79 亿美元，做空比特币流入 1,060 万美元；以太坊投资产品流出 3,900 万美元，Polkadot 和 Chainlink 分别达 70 万美元和 60 万美元；Grayscale 上周资金流出总额为 22 亿美元，新发行的美国 ETF…",
          "link": "https://twitter.com/wublockchain12/status/1751915792650875291",
          "publishedOn": "2024-01-29T10:30:48.000Z",
          "wordCount": null,
          "title": "吴说获悉，据 CoinShares，上周数字资产投资产品流出总额为 5 亿美元，其中比特币投资产品流出了 4.79 亿美元，做空比特币流入 1,060 万美元；以太坊投资产品流...",
          "imageUrl": null
        }
      ]
    },
    {
      "title": "Twitter @Deleted Account",
      "feedUrl": "https://rsshub.app/twitter/user/8848Community",
      "siteUrl": "https://twitter.com/8848Community",
      "articles": []
    },
    {
      "title": "Twitter @Onchain Wizard",
      "feedUrl": "https://rsshub.app/twitter/user/OnChainWizard",
      "siteUrl": "https://twitter.com/OnChainWizard",
      "articles": [
        {
          "id": "https://twitter.com/OnChainWizard/status/1749358387110781355",
          "author": "Onchain Wizard",
          "description": "RT Silent Protocol\nAn ecosystem - a private ecosystem of applications- that sounds big",
          "link": "https://twitter.com/OnChainWizard/status/1749358387110781355",
          "publishedOn": "2024-01-22T09:00:53.000Z",
          "wordCount": null,
          "title": "RT Silent Protocol: An ecosystem - a private ecosystem of applications- that sounds big",
          "imageUrl": null
        },
        {
          "id": "https://twitter.com/OnChainWizard/status/1749074289851089237",
          "author": "Onchain Wizard",
          "description": "Re @deficook Depin is rug central",
          "link": "https://twitter.com/OnChainWizard/status/1749074289851089237",
          "publishedOn": "2024-01-21T14:19:41.000Z",
          "wordCount": null,
          "title": "Re @deficook Depin is rug central",
          "imageUrl": null
        },
        {
          "id": "https://twitter.com/OnChainWizard/status/1748146913122144307",
          "author": "Onchain Wizard",
          "description": "Re @JeetyHendrixxx @ChainEDGE_io Woosh",
          "link": "https://twitter.com/OnChainWizard/status/1748146913122144307",
          "publishedOn": "2024-01-19T00:54:37.000Z",
          "wordCount": null,
          "title": "Re @JeetyHendrixxx @ChainEDGE_io Woosh",
          "imageUrl": null
        },
        {
          "id": "https://twitter.com/OnChainWizard/status/1748146243128225988",
          "author": "Onchain Wizard",
          "description": "Alerts from @ChainEDGE_io signaled the surprise $savm launch at $6mm -> now $40mm",
          "link": "https://twitter.com/OnChainWizard/status/1748146243128225988",
          "publishedOn": "2024-01-19T00:51:58.000Z",
          "wordCount": null,
          "title": "Alerts from @ChainEDGE_io signaled the surprise $savm launch at $6mm -> now $40mm",
          "imageUrl": null
        },
        {
          "id": "https://twitter.com/OnChainWizard/status/1747097194946015390",
          "author": "Onchain Wizard",
          "description": "A sneak peak at what kind of daily summaries you get with @ChainEDGE_io.\nFor those of us that are busy in IRL, it can help give quick context on:\n1-what notable smart money buys happened today\n2-where is the most smart money conviction\n3-a highlight of a fantastic trade",
          "link": "https://twitter.com/OnChainWizard/status/1747097194946015390",
          "publishedOn": "2024-01-16T03:23:25.000Z",
          "wordCount": null,
          "title": "A sneak peak at what kind of daily summaries you get with @ChainEDGE_io. For those of us that are busy in IRL, it can help give quick context on: 1-wh...",
          "imageUrl": null
        },
        {
          "id": "https://twitter.com/OnChainWizard/status/1747113796009672964",
          "author": "Onchain Wizard",
          "description": "RT Tomb\n</learn.> Tools To Win in the Bullah.\n>If you want to become a beast in the game you need the right tools\n>remember this is PVP\n>if you are losing its because the other player has more tools, more knowledge\n>these are some of the tools i consider to be absolutely essential for…",
          "link": "https://twitter.com/OnChainWizard/status/1747113796009672964",
          "publishedOn": "2024-01-16T02:31:50.000Z",
          "wordCount": null,
          "title": "RT Tomb: </learn.> Tools To Win in the Bullah. >If you want to become a beast in the game you need the right tools >remember this is PVP >if you are l...",
          "imageUrl": null
        },
        {
          "id": "https://twitter.com/OnChainWizard/status/1746944272568291592",
          "author": "Onchain Wizard",
          "description": "Re @KingPuchi01 @ChainEDGE_io Solana on the way",
          "link": "https://twitter.com/OnChainWizard/status/1746944272568291592",
          "publishedOn": "2024-01-15T17:15:45.000Z",
          "wordCount": null,
          "title": "Re @KingPuchi01 @ChainEDGE_io Solana on the way",
          "imageUrl": null
        },
        {
          "id": "https://twitter.com/OnChainWizard/status/1746916059922223403",
          "author": "Onchain Wizard",
          "description": "Re @KingPuchi01 @ChainEDGE_io Ask away fren",
          "link": "https://twitter.com/OnChainWizard/status/1746916059922223403",
          "publishedOn": "2024-01-15T15:23:39.000Z",
          "wordCount": null,
          "title": "Re @KingPuchi01 @ChainEDGE_io Ask away fren",
          "imageUrl": null
        },
        {
          "id": "https://twitter.com/OnChainWizard/status/1745369887214596416",
          "author": "Onchain Wizard",
          "description": "Re @TravisBickle0x Once we ship sol smart $ then we’ll know",
          "link": "https://twitter.com/OnChainWizard/status/1745369887214596416",
          "publishedOn": "2024-01-11T08:59:43.000Z",
          "wordCount": null,
          "title": "Re @TravisBickle0x Once we ship sol smart $ then we’ll know",
          "imageUrl": null
        },
        {
          "id": "https://twitter.com/OnChainWizard/status/1745366067843617107",
          "author": "Onchain Wizard",
          "description": "Re @RuneNerd_ Its sorted by number of $5k+ holders.   If the wallet counts seem low, its bc we auto refresh the wallets each week for 6 month PnL, including number of wins, no one hit wonders, etc.",
          "link": "https://twitter.com/OnChainWizard/status/1745366067843617107",
          "publishedOn": "2024-01-11T08:44:32.000Z",
          "wordCount": null,
          "title": "Re @RuneNerd_ Its sorted by number of $5k+ holders. If the wallet counts seem low, its bc we auto refresh the wallets each week for 6 month PnL, inclu...",
          "imageUrl": null
        },
        {
          "id": "https://twitter.com/OnChainWizard/status/1745365028256043489",
          "author": "Onchain Wizard",
          "description": "Smart money favorites heading into a renewed ETH season:\n$RSTK\n$MXH\n$VAULT\n$MUBI\n$OLAS",
          "link": "https://twitter.com/OnChainWizard/status/1745365028256043489",
          "publishedOn": "2024-01-11T08:40:24.000Z",
          "wordCount": null,
          "title": "Smart money favorites heading into a renewed ETH season: $RSTK $MXH $VAULT $MUBI $OLAS",
          "imageUrl": null
        },
        {
          "id": "https://twitter.com/OnChainWizard/status/1744991286203953279",
          "author": "Onchain Wizard",
          "description": "Re @RrobinjJ @227_fund @LENX_Finance It’s specific to our smart wallets.   So $47k of net buys on these lower cap coins across a smaller set of wallets is what’s interesting.",
          "link": "https://twitter.com/OnChainWizard/status/1744991286203953279",
          "publishedOn": "2024-01-10T07:55:17.000Z",
          "wordCount": null,
          "title": "Re @RrobinjJ @227_fund @LENX_Finance It’s specific to our smart wallets. So $47k of net buys on these lower cap coins across a smaller set of wallets...",
          "imageUrl": null
        },
        {
          "id": "https://twitter.com/OnChainWizard/status/1744988021802287292",
          "author": "Onchain Wizard",
          "description": "RT 227fund\nSmart Money Jan 10: Biggest Bags, Inflows & Outflows\n👜  BIGGEST BAGS 👜  \nThere’s a new token on the list. Native Bitcoin liquidity protocol $XD, from @LENX_Finance, picked up 7 SM wallets with at least 10k holdings on its launch\nAI remains the top narrative: $OLAS (20…",
          "link": "https://twitter.com/OnChainWizard/status/1744988021802287292",
          "publishedOn": "2024-01-10T07:36:08.000Z",
          "wordCount": null,
          "title": "RT 227fund: Smart Money Jan 10: Biggest Bags, Inflows & Outflows 👜 BIGGEST BAGS 👜 There’s a new token on the list. Native Bitcoin liquidity pro...",
          "imageUrl": null
        },
        {
          "id": "https://twitter.com/OnChainWizard/status/1744458177700094130",
          "author": "Onchain Wizard",
          "description": "Re @0xmandalorian We already have Avax and Sol coming thoon (Mid-Feb)",
          "link": "https://twitter.com/OnChainWizard/status/1744458177700094130",
          "publishedOn": "2024-01-08T20:36:54.000Z",
          "wordCount": null,
          "title": "Re @0xmandalorian We already have Avax and Sol coming thoon (Mid-Feb)",
          "imageUrl": null
        },
        {
          "id": "https://twitter.com/OnChainWizard/status/1743189273589776537",
          "author": "Onchain Wizard",
          "description": "With Privacy as an emerging primitive  keep an eye on @silentdao_ in 2024\n\nCrypto, Distilled: $ETH killers were the sweetest fruit of 2021.\n2024’s golden goose could be very different.\nEmerging Primitives:\n- Autonomous Economic Agents (AEAs)\n- AiDeFi (+ other DeAi verticals)\n- DePIN (storage, GPU, etc.)  \n- Privacy-Enabled Infrastructure \n- Modular Blockchains + DA\n-…",
          "link": "https://twitter.com/OnChainWizard/status/1743189273589776537",
          "publishedOn": "2024-01-05T08:34:44.000Z",
          "wordCount": null,
          "title": "With Privacy as an emerging primitive keep an eye on @silentdao_ in 2024",
          "imageUrl": null
        }
      ]
    },
    {
      "title": "Twitter @Surfer",
      "feedUrl": "https://rsshub.app/twitter/user/DeFiSurfer808",
      "siteUrl": "https://twitter.com/DeFiSurfer808",
      "articles": [
        {
          "id": "https://twitter.com/DeFiSurfer808/status/1751750832222028047",
          "author": "Surfer",
          "description": "Re @CryptoPlainview The fingers ha",
          "link": "https://twitter.com/DeFiSurfer808/status/1751750832222028047",
          "publishedOn": "2024-01-28T23:35:19.000Z",
          "wordCount": null,
          "title": "Re @CryptoPlainview The fingers ha",
          "imageUrl": null
        },
        {
          "id": "https://twitter.com/DeFiSurfer808/status/1751691557013491945",
          "author": "Surfer",
          "description": "Re @ThisIsNuse Possible",
          "link": "https://twitter.com/DeFiSurfer808/status/1751691557013491945",
          "publishedOn": "2024-01-28T19:39:46.000Z",
          "wordCount": null,
          "title": "Re @ThisIsNuse Possible",
          "imageUrl": null
        },
        {
          "id": "https://twitter.com/DeFiSurfer808/status/1751691313836155186",
          "author": "Surfer",
          "description": "Re @ZachLight16 Agree Biden should go but hard disagree we should be involved with Ukraine",
          "link": "https://twitter.com/DeFiSurfer808/status/1751691313836155186",
          "publishedOn": "2024-01-28T19:38:48.000Z",
          "wordCount": null,
          "title": "Re @ZachLight16 Agree Biden should go but hard disagree we should be involved with Ukraine",
          "imageUrl": null
        },
        {
          "id": "https://twitter.com/DeFiSurfer808/status/1751614331286859851",
          "author": "Surfer",
          "description": "Re @rev_cap Quality is over priced",
          "link": "https://twitter.com/DeFiSurfer808/status/1751614331286859851",
          "publishedOn": "2024-01-28T14:32:54.000Z",
          "wordCount": null,
          "title": "Re @rev_cap Quality is over priced",
          "imageUrl": null
        },
        {
          "id": "https://twitter.com/DeFiSurfer808/status/1751450013606015342",
          "author": "Surfer",
          "description": "Re @toptickcrypto @0xH0wl It’s def lagging at bottoms and tops",
          "link": "https://twitter.com/DeFiSurfer808/status/1751450013606015342",
          "publishedOn": "2024-01-28T03:39:58.000Z",
          "wordCount": null,
          "title": "Re @toptickcrypto @0xH0wl It’s def lagging at bottoms and tops",
          "imageUrl": null
        },
        {
          "id": "https://twitter.com/DeFiSurfer808/status/1751418675008020678",
          "author": "Surfer",
          "description": "Re @krugermacro It’s about to send too 😛",
          "link": "https://twitter.com/DeFiSurfer808/status/1751418675008020678",
          "publishedOn": "2024-01-28T01:35:26.000Z",
          "wordCount": null,
          "title": "Re @krugermacro It’s about to send too 😛",
          "imageUrl": null
        },
        {
          "id": "https://twitter.com/DeFiSurfer808/status/1751396722402533451",
          "author": "Surfer",
          "description": "Re @krugermacro Lmao",
          "link": "https://twitter.com/DeFiSurfer808/status/1751396722402533451",
          "publishedOn": "2024-01-28T00:08:12.000Z",
          "wordCount": null,
          "title": "Re @krugermacro Lmao",
          "imageUrl": null
        },
        {
          "id": "https://twitter.com/DeFiSurfer808/status/1751359334712295821",
          "author": "Surfer",
          "description": "Re @nestayxbt $300k seems too high and >80% drawdown seems too deep personally",
          "link": "https://twitter.com/DeFiSurfer808/status/1751359334712295821",
          "publishedOn": "2024-01-27T21:39:38.000Z",
          "wordCount": null,
          "title": "Re @nestayxbt $300k seems too high and >80% drawdown seems too deep personally",
          "imageUrl": null
        },
        {
          "id": "https://twitter.com/DeFiSurfer808/status/1751309936036835778",
          "author": "Surfer",
          "description": "Damn they really started the open borders policy day 1 of the administration… 😡\n\nJoe Concha: Jan 20, 2021.",
          "link": "https://twitter.com/DeFiSurfer808/status/1751309936036835778",
          "publishedOn": "2024-01-27T18:23:21.000Z",
          "wordCount": null,
          "title": "Damn they really started the open borders policy day 1 of the administration… 😡",
          "imageUrl": null
        },
        {
          "id": "https://twitter.com/DeFiSurfer808/status/1751303215822311625",
          "author": "Surfer",
          "description": "Re @RyanDetrick @carlquintanilla U still thinking we get mid fed dip?",
          "link": "https://twitter.com/DeFiSurfer808/status/1751303215822311625",
          "publishedOn": "2024-01-27T17:56:38.000Z",
          "wordCount": null,
          "title": "Re @RyanDetrick @carlquintanilla U still thinking we get mid fed dip?",
          "imageUrl": null
        },
        {
          "id": "https://twitter.com/DeFiSurfer808/status/1751302813055914339",
          "author": "Surfer",
          "description": "Re @305_Capital @NotChaseColeman It like 10x’d while he was short lmao yes he was wrong",
          "link": "https://twitter.com/DeFiSurfer808/status/1751302813055914339",
          "publishedOn": "2024-01-27T17:55:02.000Z",
          "wordCount": null,
          "title": "Re @305_Capital @NotChaseColeman It like 10x’d while he was short lmao yes he was wrong",
          "imageUrl": null
        },
        {
          "id": "https://twitter.com/DeFiSurfer808/status/1751298616952570213",
          "author": "Surfer",
          "description": "You’d be amazed how consensus “long emerging markets” still is despite its abysmal performance relative to US indexes\n\nBarchart: Emerging Market Funds just saw a weekly inflow of $12.1 billion, the largest in history 🚨🚨",
          "link": "https://twitter.com/DeFiSurfer808/status/1751298616952570213",
          "publishedOn": "2024-01-27T17:38:22.000Z",
          "wordCount": null,
          "title": "You’d be amazed how consensus “long emerging markets” still is despite its abysmal performance relative to US indexes",
          "imageUrl": null
        },
        {
          "id": "https://twitter.com/DeFiSurfer808/status/1751297168256684056",
          "author": "Surfer",
          "description": "Re @blknoiz06 I dunno bro risky to fade @hentaiavenger66",
          "link": "https://twitter.com/DeFiSurfer808/status/1751297168256684056",
          "publishedOn": "2024-01-27T17:32:37.000Z",
          "wordCount": null,
          "title": "Re @blknoiz06 I dunno bro risky to fade @hentaiavenger66",
          "imageUrl": null
        },
        {
          "id": "https://twitter.com/DeFiSurfer808/status/1751296179743146138",
          "author": "Surfer",
          "description": "Re @305_Capital That guy is insufferable",
          "link": "https://twitter.com/DeFiSurfer808/status/1751296179743146138",
          "publishedOn": "2024-01-27T17:28:41.000Z",
          "wordCount": null,
          "title": "Re @305_Capital That guy is insufferable",
          "imageUrl": null
        },
        {
          "id": "https://twitter.com/DeFiSurfer808/status/1751295851752735199",
          "author": "Surfer",
          "description": "Re @NotChaseColeman Crazier things have happened",
          "link": "https://twitter.com/DeFiSurfer808/status/1751295851752735199",
          "publishedOn": "2024-01-27T17:27:23.000Z",
          "wordCount": null,
          "title": "Re @NotChaseColeman Crazier things have happened",
          "imageUrl": null
        },
        {
          "id": "https://twitter.com/DeFiSurfer808/status/1751292993301029315",
          "author": "Surfer",
          "description": "Re @NotChaseColeman I dunno man he was pretty stubborn not willing to admit he was wrong",
          "link": "https://twitter.com/DeFiSurfer808/status/1751292993301029315",
          "publishedOn": "2024-01-27T17:16:01.000Z",
          "wordCount": null,
          "title": "Re @NotChaseColeman I dunno man he was pretty stubborn not willing to admit he was wrong",
          "imageUrl": null
        },
        {
          "id": "https://twitter.com/DeFiSurfer808/status/1751296196218421666",
          "author": "Surfer",
          "description": "RT Ryan Detrick, CMT\nWill the Fed really cut rates with stocks near ATHs?\nI found 20 times (since 1980) they cut rates when the S&P 500 was within 2% of ATHs.\nHigher a year later? 20 times. Whoa.",
          "link": "https://twitter.com/DeFiSurfer808/status/1751296196218421666",
          "publishedOn": "2024-01-27T17:08:25.000Z",
          "wordCount": null,
          "title": "RT Ryan Detrick, CMT: Will the Fed really cut rates with stocks near ATHs? I found 20 times (since 1980) they cut rates when the S&P 500 was within 2%...",
          "imageUrl": null
        },
        {
          "id": "https://twitter.com/DeFiSurfer808/status/1751283585028411565",
          "author": "Surfer",
          "description": "Re @BlacklionCTA @LynAldenContact Strong BB formatting skills",
          "link": "https://twitter.com/DeFiSurfer808/status/1751283585028411565",
          "publishedOn": "2024-01-27T16:38:38.000Z",
          "wordCount": null,
          "title": "Re @BlacklionCTA @LynAldenContact Strong BB formatting skills",
          "imageUrl": null
        },
        {
          "id": "https://twitter.com/DeFiSurfer808/status/1751283493747741172",
          "author": "Surfer",
          "description": "Oh shit\n\nBrent aka Blacklion: M2",
          "link": "https://twitter.com/DeFiSurfer808/status/1751283493747741172",
          "publishedOn": "2024-01-27T16:38:16.000Z",
          "wordCount": null,
          "title": "Oh shit",
          "imageUrl": null
        }
      ]
    }
  ],
  "cliVersion": "1.15.1"
}